timeconMT/__init__.py
timeconMT/timecon.py
timeconMT-0.0.2.dist-info/LICENSE
timeconMT-0.0.2.dist-info/METADATA
timeconMT-0.0.2.dist-info/WHEEL
timeconMT-0.0.2.dist-info/top_level.txt
timeconMT-0.0.2.dist-info/RECORD
