Metadata-Version: 2.1
Name: timeconMT
Version: 0.0.2
Summary: time converter utilities
Home-page: https://github.com/colemalphrus/timeconMT
Author: Cole Malphrus
Author-email: cole@malphrus.tech
License: UNKNOWN
Platform: UNKNOWN
Classifier: Programming Language :: Python :: 3
Classifier: License :: OSI Approved :: MIT License
Classifier: Operating System :: OS Independent
Requires-Python: >=3.6
